[
  {
    "difficulty": "easy",
    "enemy_count": 2,
    "enemies": [
      {
        "id": 5,
        "position": [
          400,
          300
        ]
      },
      {
        "id": 6,
        "position": [
          400,
          200
        ]
      }
    ]
  },
  {
    "difficulty": "medium",
    "enemy_count": 4,
    "enemies": [
      {
        "id": 0,
        "position": [
          300,
          75
        ]
      },
      {
        "id": 1,
        "position": [
          200,
          250
        ]
      },
      {
        "id": 2,
        "position": [
          800,
          245
        ]
      },
      {
        "id": 3,
        "position": [
          300,
          370
        ]
      }
    ]
  },
  {
    "difficulty": "hard",
    "enemy_count": 5,
    "enemies": [
      {
        "id": 0,
        "position": [
          300,
          75
        ]
      },
      {
        "id": 1,
        "position": [
          200,
          250
        ]
      },
      {
        "id": 2,
        "position": [
          800,
          245
        ]
      },
      {
        "id": 3,
        "position": [
          300,
          370
        ]
      },
      {
        "id": 4,
        "position": [
          500,
          300
        ]
      }
    ]
  }
]
